caj2pdf/__init__.py
caj2pdf/cajparser.py
caj2pdf/cli.py
caj2pdf/dep/__init__.py
caj2pdf/dep/decode_jbig2data.cc
caj2pdf/dep/decode_jbig2data_x.cc
caj2pdf/dep/jbig2dec.py
caj2pdf/dep/jbigdec.cc
caj2pdf/dep/jbigdec.py
caj2pdf/dep/JBigDecode.cc
caj2pdf/dep/JBigDecode.h
caj2pdf/exceptions.py
caj2pdf/exe_convert.py
caj2pdf/HNParsePage.py
caj2pdf/install.py
caj2pdf/pdfwutils.py
caj2pdf/utils.py
caj2pdf/version.py
caj2pdf/dep/bin/libjbig2codec-w32.dll
caj2pdf/dep/bin/libjbig2codec-w64.dll
caj2pdf/dep/bin/libjbigdec-w32.dll
caj2pdf/dep/bin/libjbigdec-w64.dll
lib/caj2pdf/cajparser.py
lib/caj2pdf/cli.py
lib/caj2pdf/exceptions.py
lib/caj2pdf/exe_convert.py
lib/caj2pdf/HNParsePage.py
lib/caj2pdf/install.py
lib/caj2pdf/pdfwutils.py
lib/caj2pdf/utils.py
lib/caj2pdf/version.py
lib/caj2pdf/__init__.py
lib/caj2pdf/dep/jbig2dec.py
lib/caj2pdf/dep/jbigdec.py
lib/caj2pdf/dep/__init__.py
caj2pdf_restructured-0.1.0a7.dist-info/entry_points.txt
caj2pdf_restructured-0.1.0a7.dist-info/WHEEL
caj2pdf_restructured-0.1.0a7.dist-info/METADATA
caj2pdf_restructured-0.1.0a7.dist-info/licenses/LICENSE
caj2pdf_restructured-0.1.0a7.dist-info/RECORD
