Metadata-Version: 2.1
Name: caj2pdf-restructured
Version: 0.1.0a7
Summary: caj2pdf 项目的重新组织，方便打包与安装
License: GLWTPL
Keywords: cnki,caj,pdf
Author-email: Hin-Tak Leung <htl10@users.sourceforge.net>,JeziL <wangjinlithu@gmail.com>
Maintainer-email: zombie110year <zombie110year@outlook.com>
Requires-Python: >=3.10
Classifier: Environment :: Console
Classifier: Operating System :: Microsoft :: Windows
Classifier: Operating System :: POSIX :: Linux
Requires-Dist: PyPDF2==2.2.0
Requires-Dist: imagesize==1.3.0
Project-URL: repository, https://github.com/zombie110year/caj2pdf-restructured/
